[{"categories":null,"content":"✨关于本博客 这是一个通过Hugo和Github搭建而成的静态博客，模板使用的是LoveIt。相关教程网上已经有很多，如果你也对搭建自己的博客感兴趣，请务必试一试👏🏻 ✨关于我 ","date":"2022-09-13","objectID":"/about/:0:0","tags":null,"title":"关于","uri":"/about/"},{"categories":null,"content":"🥚自我介绍 你好，我是蛋白！ 透明漫画作者，主耽美. 笔名是lamatter。初中起的，是《家庭教师Reborn》的Lambo，和电影版《爱丽丝漫游仙境》的疯帽子Hatter结合而成的名字。我也没有想到初中随便起的用户名会变成笔名…… 日狮月瓶升瓶，过去8年都是INFP,近两年却测出了INTP,INFJ,ISFP,ISTP等等所以现在也不确定自己是什么类型。 喜欢成天看一些乱七八糟的东西 喜欢的耽美漫画作者有：中村明日美子、国枝彩香、朝田ねむい 喜欢能平衡好幽默和故事主线、人物塑造丰满的作品。 常年作品荒，欢迎推荐 \u003e_\u003c ","date":"2022-09-13","objectID":"/about/:0:1","tags":null,"title":"关于","uri":"/about/"},{"categories":null,"content":"📚我的作品 四格|当不良老大的男人（坑）（2016.1-） →本站汇总 页漫|当不良老大的男人（已完结）（2016.12-2019.9） →快看 →哔漫 条漫|今夜晚风吹拂（已完结）（2020.1-2020.12） →快看 条漫|完美恋人的失控（暂时坑）（2022.12-） ","date":"2022-09-13","objectID":"/about/:0:2","tags":null,"title":"关于","uri":"/about/"},{"categories":null,"content":"🔮之后打算 1.完成《失控》 2.尝试新的短篇和分镜手法 ","date":"2022-09-13","objectID":"/about/:0:3","tags":null,"title":"关于","uri":"/about/"},{"categories":null,"content":"🌵其他 放一个微博小号，有事没事来聊天！ ","date":"2022-09-13","objectID":"/about/:0:4","tags":null,"title":"关于","uri":"/about/"},{"categories":["漫画"],"content":"继续回顾","date":"2022-09-14","objectID":"/posts/%E4%B8%8D%E8%89%AF10/","tags":["不良","耽美"],"title":"四格|不良第10话","uri":"/posts/%E4%B8%8D%E8%89%AF10/"},{"categories":["漫画"],"content":"戛然而止","date":"2022-09-14","objectID":"/posts/%E4%B8%8D%E8%89%AF11/","tags":["不良","耽美"],"title":"四格|不良第11话","uri":"/posts/%E4%B8%8D%E8%89%AF11/"},{"categories":["漫画"],"content":"一切的起点","date":"2022-09-14","objectID":"/posts/%E4%B8%8D%E8%89%AF1/","tags":["不良","耽美"],"title":"四格|不良第1话","uri":"/posts/%E4%B8%8D%E8%89%AF1/"},{"categories":["漫画"],"content":"一边上传一边回顾","date":"2022-09-14","objectID":"/posts/%E4%B8%8D%E8%89%AF2/","tags":["不良","耽美"],"title":"四格|不良第2话","uri":"/posts/%E4%B8%8D%E8%89%AF2/"},{"categories":["漫画"],"content":"似乎想尝试一些不一样的","date":"2022-09-14","objectID":"/posts/%E4%B8%8D%E8%89%AF3/","tags":["不良","耽美"],"title":"四格|不良第3话","uri":"/posts/%E4%B8%8D%E8%89%AF3/"},{"categories":["漫画"],"content":"王天霸本篇大放异彩，可惜页漫里没有你","date":"2022-09-14","objectID":"/posts/%E4%B8%8D%E8%89%AF4/","tags":["不良","耽美"],"title":"四格|不良第4话","uri":"/posts/%E4%B8%8D%E8%89%AF4/"},{"categories":["漫画"],"content":"开始讲学校了","date":"2022-09-14","objectID":"/posts/%E4%B8%8D%E8%89%AF5/","tags":["不良","耽美"],"title":"四格|不良第5话","uri":"/posts/%E4%B8%8D%E8%89%AF5/"},{"categories":["漫画"],"content":"开始看不懂在讲什么了","date":"2022-09-14","objectID":"/posts/%E4%B8%8D%E8%89%AF6/","tags":["不良","耽美"],"title":"四格|不良第6话","uri":"/posts/%E4%B8%8D%E8%89%AF6/"},{"categories":["漫画"],"content":"副cp，当时真打算画的，从初中就开始构思了这对","date":"2022-09-14","objectID":"/posts/%E4%B8%8D%E8%89%AF7/","tags":["不良","耽美"],"title":"四格|不良第7话","uri":"/posts/%E4%B8%8D%E8%89%AF7/"},{"categories":["漫画"],"content":"日常","date":"2022-09-14","objectID":"/posts/%E4%B8%8D%E8%89%AF8/","tags":["不良","耽美"],"title":"四格|不良第8话","uri":"/posts/%E4%B8%8D%E8%89%AF8/"},{"categories":["漫画"],"content":"嗯嗯嗯……","date":"2022-09-14","objectID":"/posts/%E4%B8%8D%E8%89%AF9/","tags":["不良","耽美"],"title":"四格|不良第9话","uri":"/posts/%E4%B8%8D%E8%89%AF9/"},{"categories":["漫画"],"content":"如果在阅读时感到中二得难以忍受，没错，这就是这个故事原本要表达的","date":"2022-09-14","objectID":"/posts/%E4%B8%8D%E8%89%AF%E6%B1%87%E6%80%BB/","tags":["不良","耽美","汇总"],"title":"四格|当不良老大的男人1-11话汇总","uri":"/posts/%E4%B8%8D%E8%89%AF%E6%B1%87%E6%80%BB/"},{"categories":["漫画"],"content":"本作于2016.1-2016.8上传于有妖气平台，后来因为转为彩色页漫，这个黑白四格版本就下架了 虽然是不成熟的黑历史，但作为第一次尝试漫画连载，仍然是珍贵的回忆，所以在这里存放和汇总一下 （这里是正式连载的地址↓） 快看 / 哔漫 📕正文 四格|不良第1话 四格|不良第2话 四格|不良第3话 四格|不良第4话 四格|不良第5话 四格|不良第6话 四格|不良第7话 四格|不良第8话 四格|不良第9话 四格|不良第10话 四格|不良第11话 🧐关于本作的名字 作为一个恋爱漫画来说，《当不良老大的男人》这个名字确实显得有些风格迥异。但它其实是基于多方面考量后才决定的名字 尽管时隔完结很久，但我一定要专门找个地方解释一下，本作名字的由来 ","date":"2022-09-14","objectID":"/posts/%E4%B8%8D%E8%89%AF%E6%B1%87%E6%80%BB/:0:0","tags":["不良","耽美","汇总"],"title":"四格|当不良老大的男人1-11话汇总","uri":"/posts/%E4%B8%8D%E8%89%AF%E6%B1%87%E6%80%BB/"},{"categories":["漫画"],"content":"1. 它是一个双关，来源于多年前的网络梗。不知道还有没有人记得 “我是要当上海贼王的男人”“上海没有贼王”“海贼王有男人？” 虽然作者没怎么看过海贼王，但她真的很喜欢这种无聊的网络梗…… ","date":"2022-09-14","objectID":"/posts/%E4%B8%8D%E8%89%AF%E6%B1%87%E6%80%BB/:0:1","tags":["不良","耽美","汇总"],"title":"四格|当不良老大的男人1-11话汇总","uri":"/posts/%E4%B8%8D%E8%89%AF%E6%B1%87%E6%80%BB/"},{"categories":["漫画"],"content":"2. 本作最初是个搞笑沙雕四格漫画。这个名字其实很契合漫画最初的风格 ","date":"2022-09-14","objectID":"/posts/%E4%B8%8D%E8%89%AF%E6%B1%87%E6%80%BB/:0:2","tags":["不良","耽美","汇总"],"title":"四格|当不良老大的男人1-11话汇总","uri":"/posts/%E4%B8%8D%E8%89%AF%E6%B1%87%E6%80%BB/"},{"categories":["漫画"],"content":"3. 本作发布时间是16年初 当时的有妖气，人才济济 而读者在首页能一眼看到的，只有众多漫画的封面和名字 该怎样，仅凭封面和名字吸引读者，让她们在这么多作品中，一眼就看到本作呢？ 作者最终在某论坛找到了起名秘诀（若您也创作，却苦于不会起名，我将在这里传授给您这个秘诀），也就是——： 新人作者呀，千万不要起一些文艺漂亮、但是根本看不出来内容讲什么的名字，作品的名字要起得越通俗易懂、越有冲突感，越好！ 比如霸道总裁小娇妻、重生之黑莲花逆袭、穿越三国之一笑倾城……诸如此类。 一看就知道讲的什么 朴素的名字，恰恰蕴含着深厚的商业智慧。 你学会了吗？ 作者从那篇帖子里获益良多，大受启发，最后潜心研究，想出了“当不良老大的男人”这个了不得的名字 ","date":"2022-09-14","objectID":"/posts/%E4%B8%8D%E8%89%AF%E6%B1%87%E6%80%BB/:0:3","tags":["不良","耽美","汇总"],"title":"四格|当不良老大的男人1-11话汇总","uri":"/posts/%E4%B8%8D%E8%89%AF%E6%B1%87%E6%80%BB/"},{"categories":["漫画"],"content":"4. …… 我后来花了很长时间跟这个名字和解。 四格转到页漫以后，这个名字跟新的故事的风格有一些出入，甚至一度影响到我对故事走向的构思。（名字太中二，故事却越来越正经，有点割裂。） 想过要改，但又觉得算了。尴尬着就尴尬出感情来了。 其实我最害怕的倒不是羞耻 而是给读者造出一种高的期待，等到读者点进来细细看内容，又大失所望 我最害怕让人期待落空 所以这个名字最大的好处就是，不会给读者什么期待。 （应该不会有期待吧？对这种名字还有期待的人请反省一下自己好不好！是不是其实在期待看到一些啼笑皆非的东西……） —————————————————————— 有一天，一个读者点进来，说： “看名字以为是个玛丽苏/杰克苏漫画，没想到看完发现，居然是一个暖心小故事呢！” 这种“没想到吧”，的乐趣，很大程度上缓解了我的羞耻感。 由于大家并没有对这个作品抱有什么期待，所以只要漫画内容稍微有一点点可取之处，就会超出大家不是很高的预期，制造一种惊喜感 （也可能是别的吧我也不知道） ","date":"2022-09-14","objectID":"/posts/%E4%B8%8D%E8%89%AF%E6%B1%87%E6%80%BB/:0:4","tags":["不良","耽美","汇总"],"title":"四格|当不良老大的男人1-11话汇总","uri":"/posts/%E4%B8%8D%E8%89%AF%E6%B1%87%E6%80%BB/"},{"categories":["漫画"],"content":"5. 解释了这么多，可能还是没办法缓解那种中二感 哎呀没关系， 反正， 年轻人嘛就是中二的啦！啊那还想要怎样啊！！ ","date":"2022-09-14","objectID":"/posts/%E4%B8%8D%E8%89%AF%E6%B1%87%E6%80%BB/:0:5","tags":["不良","耽美","汇总"],"title":"四格|当不良老大的男人1-11话汇总","uri":"/posts/%E4%B8%8D%E8%89%AF%E6%B1%87%E6%80%BB/"}]